{"stats":{"minecraft:custom":{"minecraft:interact_with_furnace":18,"minecraft:inspect_dropper":3,"minecraft:mob_kills":26,"minecraft:animals_bred":3,"minecraft:traded_with_villager":1,"minecraft:interact_with_crafting_table":120,"minecraft:open_barrel":4,"minecraft:open_shulker_box":12,"minecraft:bell_ring":37,"minecraft:pot_flower":2,"minecraft:leave_game":459,"minecraft:time_since_death":1813344,"minecraft:climb_one_cm":396,"minecraft:time_since_rest":1813344,"minecraft:sprint_one_cm":1424331,"minecraft:damage_taken":1060,"minecraft:walk_one_cm":3075152,"minecraft:drop":99,"minecraft:damage_dealt":3875,"minecraft:swim_one_cm":1853,"minecraft:talked_to_villager":5,"minecraft:fly_one_cm":2321798,"minecraft:open_chest":23,"minecraft:crouch_one_cm":22530,"minecraft:play_time":1813344,"minecraft:sneak_time":13885,"minecraft:walk_under_water_one_cm":11417,"minecraft:jump":6324,"minecraft:interact_with_blast_furnace":47,"minecraft:walk_on_water_one_cm":21052,"minecraft:total_world_time":2699724,"minecraft:fall_one_cm":18665,"minecraft:inspect_dispenser":2},"minecraft:crafted":{"patchouli:guide_book":1,"minecraft:air":0,"minecraft:dark_oak_slab":6,"coffeecraft:bag_coffee_roasted":1},"minecraft:dropped":{"coffeecraft:roaster_animated":1,"minecraft:crafting_table":2,"coffeecraft:roaster":1,"patchouli:guide_book":4,"minecraft:blast_furnace":1,"minecraft:dirt":2,"minecraft:wooden_shovel":1,"minecraft:string":2},"minecraft:picked_up":{"minecraft:crafting_table":2,"minecraft:water_bucket":1,"minecraft:leather":2,"minecraft:lead":1,"minecraft:dirt":1,"minecraft:string":11,"minecraft:paper":8,"minecraft:lantern":1,"coffeecraft:roaster":1,"minecraft:item_frame":9,"minecraft:pufferfish":1,"minecraft:bone":2,"coffeecraft:red_mug":24,"minecraft:wheat_seeds":4,"minecraft:creeper_spawn_egg":64,"minecraft:bell":2,"minecraft:dark_oak_door":1,"coffeecraft:roaster_animated":1,"patchouli:guide_book":2,"minecraft:porkchop":2,"minecraft:ink_sac":2,"coffeecraft:coffee_bean":72,"coffeecraft:coffee_cherry":13,"minecraft:arrow":2,"minecraft:mangrove_door":3,"minecraft:terracotta":61,"minecraft:white_shulker_box":4,"minecraft:coal":592,"minecraft:ender_pearl":1},"minecraft:killed":{"minecraft:cat":10,"minecraft:pig":1,"minecraft:spider":2,"minecraft:wandering_trader":2,"minecraft:zombie_horse":1,"minecraft:pufferfish":1,"minecraft:phantom":1,"minecraft:trader_llama":3,"minecraft:panda":1,"minecraft:villager":2,"minecraft:enderman":1},"minecraft:used":{"minecraft:chiseled_polished_blackstone":75,"minecraft:zombie_horse_spawn_egg":1,"minecraft:quartz_bricks":103,"minecraft:wheat_seeds":2,"minecraft:dark_oak_stairs":207,"minecraft:water_bucket":4,"minecraft:netherite_sword":31,"minecraft:writable_book":8,"minecraft:dropper":2,"minecraft:flint_and_steel":6,"minecraft:armor_stand":6,"minecraft:dispenser":1,"minecraft:redstone":7,"minecraft:pufferfish_spawn_egg":4,"minecraft:mangrove_fence_gate":1,"minecraft:oak_sign":10,"coffeecraft:coffee_maker_white_empty":8,"minecraft:chest":3,"minecraft:spruce_planks":189,"minecraft:redstone_block":10,"minecraft:white_shulker_box":7,"minecraft:wooden_shovel":16,"minecraft:bell":9,"minecraft:spruce_fence_gate":6,"minecraft:quartz_stairs":15,"minecraft:stone_hoe":2,"minecraft:torch":1,"minecraft:dirt":25,"minecraft:orange_carpet":48,"coffeecraft:roaster":4,"minecraft:oak_slab":1,"minecraft:white_carpet":29,"minecraft:crafting_table":18,"minecraft:red_bed":1,"coffeecraft:coffee_cherry":18,"coffeecraft:roaster_animated":20,"minecraft:phantom_spawn_egg":1,"minecraft:blast_furnace":12,"minecraft:campfire":1,"minecraft:painting":95,"minecraft:spruce_log":40,"minecraft:dark_oak_door":2,"minecraft:milk_bucket":40,"minecraft:enderman_spawn_egg":1,"minecraft:creeper_spawn_egg":15,"minecraft:redstone_torch":5,"minecraft:oak_log":88,"minecraft:piston":7,"minecraft:dark_oak_planks":102,"coffeecraft:bag_coffee_roasted":59,"minecraft:flower_pot":3,"minecraft:wooden_hoe":12,"minecraft:lever":3,"minecraft:lava_bucket":6,"coffeecraft:grinder":1,"minecraft:villager_spawn_egg":2,"minecraft:mangrove_door":14,"minecraft:cherry_door":1,"minecraft:panda_spawn_egg":1,"minecraft:heavy_weighted_pressure_plate":4,"minecraft:quartz_slab":24,"coffeecraft:coffee_fluid_bucket":53,"minecraft:lantern":11,"minecraft:grass_block":134,"minecraft:oak_stairs":3,"geckolib:gecko_habitat":1,"minecraft:stone_button":1,"minecraft:quartz_block":56,"minecraft:dark_oak_slab":48,"minecraft:spruce_trapdoor":18,"coffeecraft:red_mug":10,"coffeecraft:grinder_anim":2,"minecraft:cat_spawn_egg":7,"minecraft:item_frame":11,"minecraft:barrel":8,"minecraft:stone_bricks":46,"coffeecraft:coffee_maker_black_empty":8,"minecraft:diamond_sword":10,"minecraft:repeater":2,"minecraft:bow":8,"minecraft:written_book":12,"coffeecraft:croissant":10,"minecraft:furnace":9,"minecraft:glass_pane":35,"minecraft:white_stained_glass_pane":6,"minecraft:chain":8,"minecraft:bucket":66,"minecraft:smooth_stone_slab":25,"minecraft:oak_hanging_sign":1},"minecraft:mined":{"coffeecraft:red_mug_3":5,"coffeecraft:red_mug":1,"minecraft:grass":2,"coffeecraft:red_mug_2":4,"minecraft:white_shulker_box":1}},"DataVersion":3465}